rtl/alu.v
`timescale 1ns/1ps

// ============================================================
// alu.v — RV32I ALU
// Supports: ADD, SUB, SLL, SLT, SLTU, XOR, SRL, SRA, OR, AND
// alu_op encoding matches control.v
// ============================================================
module alu #(
    parameter DATA_WIDTH = 32
)(
    input  [DATA_WIDTH-1:0] a,
    input  [DATA_WIDTH-1:0] b,
    input  [3:0]            alu_op,
    input  [2:0]            funct3,   // needed to pick SRL vs SRA, ADD vs SUB
    input                   funct7_5, // bit 30 of instr → SUB/SRA selector
    output reg [DATA_WIDTH-1:0] result,
    output zero
);

    wire [4:0] shamt = b[4:0]; // shift amount = lower 5 bits

    always @(*) begin
        case (alu_op)
            4'b0000: result = a + b;                              // ADD / ADDI / LW / SW / JAL
            4'b0001: result = a - b;                              // SUB / BEQ compare
            4'b0010: result = a << shamt;                         // SLL / SLLI
            4'b0011: result = ($signed(a) < $signed(b)) ? 32'd1 : 32'd0; // SLT / SLTI
            4'b0100: result = (a < b) ? 32'd1 : 32'd0;           // SLTU / SLTIU
            4'b0101: result = a ^ b;                              // XOR / XORI
            4'b0110: result = a >> shamt;                         // SRL / SRLI
            4'b0111: result = $signed(a) >>> shamt;               // SRA / SRAI
            4'b1000: result = a | b;                              // OR  / ORI
            4'b1001: result = a & b;                              // AND / ANDI
            4'b1010: result = a;                                  // PASS-A (for JAL/JALR)
            default: result = 32'h0;
        endcase
    end

    assign zero = (result == 32'h0);

endmodule

rtl/imm_gen.v
`timescale 1ns/1ps

module imm_gen(
    input  [31:0] instr,
    output reg [31:0] imm
);

    wire [6:0] opcode = instr[6:0];

    always @(*) begin
        case (opcode)
            // I-type (ADDI, LW, JALR)
            7'b0010011, // ADDI
            7'b0000011, // LW
            7'b1100111: // JALR
                imm = {{20{instr[31]}}, instr[31:20]};
            
            // S-type (SW)
            7'b0100011:
                imm = {{20{instr[31]}}, instr[31:25], instr[11:7]};
            
            // B-type (BEQ, BNE, etc.) - offset in bytes, multiplied by 2
            7'b1100011:
                imm = {{19{instr[31]}}, instr[31], instr[7], instr[30:25], instr[11:8], 1'b0};
            
            // J-type (JAL) - IMPORTANT: scattered immediate bits
            7'b1101111:
                imm = {{11{instr[31]}}, instr[31], instr[19:12], instr[20], instr[30:21], 1'b0};
            
            // U-type (LUI, AUIPC)
            7'b0110111, // LUI
            7'b0010111: // AUIPC
                imm = {instr[31:12], 12'b0};
            
            default:
                imm = 32'b0;
        endcase
    end

endmodule

rtl/control.v
`timescale 1ns/1ps

// ============================================================
// control.v — RV32I Control Unit
// Decodes opcode → control signals for pipeline_cpu.v
// ============================================================
module control(
    input  [6:0] opcode,
    output reg [3:0] alu_op,
    output reg alu_src,
    output reg mem_to_reg,
    output reg reg_write,
    output reg mem_read,
    output reg mem_write,
    output reg branch,
    output reg jal,
    output reg jalr
);

    // RISC-V Opcodes
    localparam OP_R      = 7'b0110011; // R-type  (add, sub, and, or, xor, sll, srl, sra, slt)
    localparam OP_I_ALU  = 7'b0010011; // I-type  (addi, andi, ori, xori, slli, srli, srai, slti)
    localparam OP_LOAD   = 7'b0000011; // Load    (lw)
    localparam OP_STORE  = 7'b0100011; // Store   (sw)
    localparam OP_BRANCH = 7'b1100011; // Branch  (beq, bne, blt)
    localparam OP_JAL    = 7'b1101111; // JAL
    localparam OP_JALR   = 7'b1100111; // JALR

    // ALU op encoding (must match alu.v)
    localparam ALU_ADD  = 4'b0000;
    localparam ALU_SUB  = 4'b0001;
    localparam ALU_SLL  = 4'b0010;
    localparam ALU_SLT  = 4'b0011;
    localparam ALU_SLTU = 4'b0100;
    localparam ALU_XOR  = 4'b0101;
    localparam ALU_SRL  = 4'b0110;
    localparam ALU_SRA  = 4'b0111;
    localparam ALU_OR   = 4'b1000;
    localparam ALU_AND  = 4'b1001;
    localparam ALU_PASS = 4'b1010; // pass a (for JAL/JALR PC+4)

    always @(*) begin
        // Safe defaults — NOP
        alu_op    = ALU_ADD;
        alu_src   = 0;
        mem_to_reg= 0;
        reg_write = 0;
        mem_read  = 0;
        mem_write = 0;
        branch    = 0;
        jal       = 0;
        jalr      = 0;

        case (opcode)
            OP_R: begin
                // funct3/funct7 decoded in EX stage via alu_op from ID
                // control just enables reg write, ALU uses regs
                alu_op    = ALU_ADD;  // placeholder; EX overrides via funct
                alu_src   = 0;
                reg_write = 1;
            end

            OP_I_ALU: begin
                alu_op    = ALU_ADD;  // placeholder; EX overrides via funct
                alu_src   = 1;        // use immediate
                reg_write = 1;
            end

            OP_LOAD: begin
                alu_op    = ALU_ADD;
                alu_src   = 1;
                mem_to_reg= 1;
                reg_write = 1;
                mem_read  = 1;
            end

            OP_STORE: begin
                alu_op    = ALU_ADD;
                alu_src   = 1;
                mem_write = 1;
            end

            OP_BRANCH: begin
                alu_op    = ALU_SUB;  // SUB → zero flag for BEQ
                alu_src   = 0;
                branch    = 1;
            end

            OP_JAL: begin
                alu_op    = ALU_ADD;
                jal       = 1;
                reg_write = 1;        // write PC+4 to rd
            end

            OP_JALR: begin
                alu_op    = ALU_ADD;
                alu_src   = 1;
                jalr      = 1;
                reg_write = 1;
            end

            default: begin
                // NOP / unknown — all zeros
            end
        endcase
    end

endmodule

pipeline_cpu.v
`timescale 1ns / 1ps

// ============================================================
// pipeline_cpu.v — 5-Stage Pipelined RISC-V RV32I CPU
//
// Fixes vs original:
//  1. JAL/branch FLUSH of IF_ID register (was missing → PC=40 bug)
//  2. JAL writes PC+4 to rd (not ALU result)
//  3. Full RV32I ALU op decoding in EX stage (funct3/funct7)
//  4. WB forwarding uses wb_data (covers load→use via MEM_WB)
//  5. Load-use stall inserts bubble into ID_EX correctly
//  6. CPI performance counter added
// ============================================================
module pipeline_cpu(
    input clk,
    input rst
);

// ============================================================
// IF STAGE — Instruction Fetch
// ============================================================
    reg  [31:0] PC;
    wire [31:0] pc_plus4;
    wire [31:0] instr;

    reg [31:0] instr_mem [0:255];
    initial $readmemh("program.hex", instr_mem);

    assign pc_plus4 = PC + 4;
    assign instr    = instr_mem[PC[9:2]];

    // Stall and flush control wires (declared early, driven later)
    wire stall;        // load-use hazard stall
    wire flush_if_id; // flush on taken branch or JAL

    always @(posedge clk or posedge rst) begin
        if (rst)
            PC <= 32'h0;
        else if (!stall)
            PC <= pc_next;
    end

// ============================================================
// IF/ID PIPELINE REGISTER
// ============================================================
    reg [31:0] IF_ID_pc, IF_ID_instr;

    wire [6:0] IF_ID_opcode = IF_ID_instr[6:0];
    wire [4:0] IF_ID_rs1    = IF_ID_instr[19:15];
    wire [4:0] IF_ID_rs2    = IF_ID_instr[24:20];
    wire [4:0] IF_ID_rd     = IF_ID_instr[11:7];

    always @(posedge clk or posedge rst) begin
        if (rst) begin
            IF_ID_pc    <= 32'h0;
            IF_ID_instr <= 32'h00000013; // NOP
        end else if (flush_if_id) begin
            // FIX 1: flush the wrong instruction fetched after JAL/branch
            IF_ID_pc    <= 32'h0;
            IF_ID_instr <= 32'h00000013; // NOP
        end else if (!stall) begin
            IF_ID_pc    <= PC;
            IF_ID_instr <= instr;
        end
        // if stall: hold current IF_ID (do nothing)
    end

// ============================================================
// ID STAGE — Instruction Decode + Register Read
// ============================================================
    wire [31:0] imm_out;
    wire [3:0]  ctrl_alu_op;
    wire        ctrl_alu_src, ctrl_mem_to_reg, ctrl_reg_write;
    wire        ctrl_mem_read, ctrl_mem_write, ctrl_branch;
    wire        ctrl_jal, ctrl_jalr;

    control ctrl_inst(
        .opcode    (IF_ID_opcode),
        .alu_op    (ctrl_alu_op),
        .alu_src   (ctrl_alu_src),
        .mem_to_reg(ctrl_mem_to_reg),
        .reg_write (ctrl_reg_write),
        .mem_read  (ctrl_mem_read),
        .mem_write (ctrl_mem_write),
        .branch    (ctrl_branch),
        .jal       (ctrl_jal),
        .jalr      (ctrl_jalr)
    );

    imm_gen imm_gen_inst(
        .instr(IF_ID_instr),
        .imm  (imm_out)
    );

    // Register File
    reg  [31:0] regs [0:31];
    wire [31:0] reg_rdata1, reg_rdata2;

    assign reg_rdata1 = (IF_ID_rs1 == 0) ? 32'h0 : regs[IF_ID_rs1];
    assign reg_rdata2 = (IF_ID_rs2 == 0) ? 32'h0 : regs[IF_ID_rs2];

    integer k;
    initial begin
        for (k = 0; k < 32; k = k + 1) regs[k] = 32'h0;
    end

// ============================================================
// WB STAGE signals (declared here, used in WB + forwarding)
// ============================================================
    reg  [31:0] reg_wdata_wb;
    reg  [4:0]  reg_waddr_wb;
    reg         reg_write_wb;

    always @(posedge clk) begin
        if (reg_write_wb && (reg_waddr_wb != 5'h0))
            regs[reg_waddr_wb] <= reg_wdata_wb;
    end

// ============================================================
// HAZARD DETECTION — Load-Use Stall
// ============================================================
    // Stall when EX stage has a load AND destination matches ID source
    assign stall = (ID_EX_mem_read &&
                    (ID_EX_rd != 5'h0) &&
                    ((ID_EX_rd == IF_ID_rs1) || (ID_EX_rd == IF_ID_rs2)));

    // FIX 1: Flush IF/ID when JAL or taken branch resolves in EX stage
    wire branch_taken = ID_EX_branch && alu_zero;
    assign flush_if_id = (ID_EX_jal || branch_taken || ID_EX_jalr);

// ============================================================
// ID/EX PIPELINE REGISTER
// ============================================================
    reg [31:0] ID_EX_pc, ID_EX_reg_rdata1, ID_EX_reg_rdata2, ID_EX_imm;
    reg [4:0]  ID_EX_rs1, ID_EX_rs2, ID_EX_rd;
    reg [3:0]  ID_EX_alu_op;
    reg [2:0]  ID_EX_funct3;
    reg        ID_EX_funct7_5;
    reg        ID_EX_alu_src, ID_EX_mem_to_reg, ID_EX_reg_write;
    reg        ID_EX_mem_read, ID_EX_mem_write, ID_EX_branch;
    reg        ID_EX_jal, ID_EX_jalr;

    always @(posedge clk or posedge rst) begin
        if (rst || stall) begin
            // Insert NOP bubble on stall
            ID_EX_pc          <= 32'h0;
            ID_EX_reg_rdata1  <= 32'h0;
            ID_EX_reg_rdata2  <= 32'h0;
            ID_EX_imm         <= 32'h0;
            ID_EX_rs1         <= 5'h0;
            ID_EX_rs2         <= 5'h0;
            ID_EX_rd          <= 5'h0;
            ID_EX_alu_op      <= 4'h0;
            ID_EX_funct3      <= 3'h0;
            ID_EX_funct7_5    <= 1'b0;
            ID_EX_alu_src     <= 1'b0;
            ID_EX_mem_to_reg  <= 1'b0;
            ID_EX_reg_write   <= 1'b0;
            ID_EX_mem_read    <= 1'b0;
            ID_EX_mem_write   <= 1'b0;
            ID_EX_branch      <= 1'b0;
            ID_EX_jal         <= 1'b0;
            ID_EX_jalr        <= 1'b0;
        end else begin
            ID_EX_pc          <= IF_ID_pc;
            ID_EX_reg_rdata1  <= reg_rdata1;
            ID_EX_reg_rdata2  <= reg_rdata2;
            ID_EX_imm         <= imm_out;
            ID_EX_rs1         <= IF_ID_rs1;
            ID_EX_rs2         <= IF_ID_rs2;
            ID_EX_rd          <= IF_ID_rd;
            ID_EX_alu_op      <= ctrl_alu_op;
            ID_EX_funct3      <= IF_ID_instr[14:12];
            ID_EX_funct7_5    <= IF_ID_instr[30];
            ID_EX_alu_src     <= ctrl_alu_src;
            ID_EX_mem_to_reg  <= ctrl_mem_to_reg;
            ID_EX_reg_write   <= ctrl_reg_write;
            ID_EX_mem_read    <= ctrl_mem_read;
            ID_EX_mem_write   <= ctrl_mem_write;
            ID_EX_branch      <= ctrl_branch;
            ID_EX_jal         <= ctrl_jal;
            ID_EX_jalr        <= ctrl_jalr;
        end
    end

// ============================================================
// EX STAGE — Execute
// ============================================================

    // FIX 3: Decode actual ALU operation from funct3/funct7 in EX
    reg [3:0] ex_alu_op;
    always @(*) begin
        ex_alu_op = ID_EX_alu_op; // default from control
        case (IF_ID_opcode) // use ID_EX opcode context via funct3
            default: begin
                // R-type and I-type ALU: decode from funct3
                case (ID_EX_funct3)
                    3'b000: ex_alu_op = (ID_EX_funct7_5 && !ID_EX_alu_src)
                                         ? 4'b0001  // SUB (R-type only)
                                         : 4'b0000; // ADD / ADDI
                    3'b001: ex_alu_op = 4'b0010; // SLL / SLLI
                    3'b010: ex_alu_op = 4'b0011; // SLT / SLTI
                    3'b011: ex_alu_op = 4'b0100; // SLTU / SLTIU
                    3'b100: ex_alu_op = 4'b0101; // XOR / XORI
                    3'b101: ex_alu_op = ID_EX_funct7_5
                                         ? 4'b0111  // SRA / SRAI
                                         : 4'b0110; // SRL / SRLI
                    3'b110: ex_alu_op = 4'b1000; // OR  / ORI
                    3'b111: ex_alu_op = 4'b1001; // AND / ANDI
                    default: ex_alu_op = 4'b0000;
                endcase
            end
        endcase
    end

    // Forwarding Unit
    // FIX 4: Forward wb_data (not just alu_result) from MEM/WB stage
    wire [31:0] wb_data = (MEM_WB_mem_to_reg) ? MEM_WB_mem_data : MEM_WB_alu_result;

    wire [1:0] forward_a_sel, forward_b_sel;
    assign forward_a_sel =
        (EX_MEM_reg_write && (EX_MEM_rd != 0) && (EX_MEM_rd == ID_EX_rs1)) ? 2'b10 :
        (MEM_WB_reg_write && (MEM_WB_rd != 0) && (MEM_WB_rd == ID_EX_rs1)) ? 2'b01 :
        2'b00;

    assign forward_b_sel =
        (EX_MEM_reg_write && (EX_MEM_rd != 0) && (EX_MEM_rd == ID_EX_rs2)) ? 2'b10 :
        (MEM_WB_reg_write && (MEM_WB_rd != 0) && (MEM_WB_rd == ID_EX_rs2)) ? 2'b01 :
        2'b00;

    wire [31:0] forward_a_out, forward_b_out;
    assign forward_a_out =
        (forward_a_sel == 2'b10) ? EX_MEM_alu_result :
        (forward_a_sel == 2'b01) ? wb_data :           // FIX 4
        ID_EX_reg_rdata1;

    assign forward_b_out =
        (forward_b_sel == 2'b10) ? EX_MEM_alu_result :
        (forward_b_sel == 2'b01) ? wb_data :           // FIX 4
        ID_EX_reg_rdata2;

    wire [31:0] alu_in_a = forward_a_out;
    wire [31:0] alu_in_b = ID_EX_alu_src ? ID_EX_imm : forward_b_out;

    wire [31:0] alu_result;
    wire        alu_zero;

    alu alu_inst(
        .a       (alu_in_a),
        .b       (alu_in_b),
        .alu_op  (ex_alu_op),
        .funct3  (ID_EX_funct3),
        .funct7_5(ID_EX_funct7_5),
        .result  (alu_result),
        .zero    (alu_zero)
    );

    // Branch / Jump target
    wire [31:0] branch_target = ID_EX_pc + ID_EX_imm;
    wire [31:0] jal_target    = ID_EX_pc + ID_EX_imm;
    wire [31:0] jalr_target   = {alu_result[31:1], 1'b0};

    // FIX 2: JAL writes PC+4 to rd — use pc_plus4_ex for that
    wire [31:0] pc_plus4_ex   = ID_EX_pc + 4;

    wire [31:0] pc_next =
        ID_EX_jal              ? jal_target    :
        (ID_EX_branch && alu_zero) ? branch_target :
        ID_EX_jalr             ? jalr_target   :
        pc_plus4;

// ============================================================
// EX/MEM PIPELINE REGISTER
// ============================================================
    reg [31:0] EX_MEM_alu_result, EX_MEM_reg_rdata2;
    reg [31:0] EX_MEM_pc_plus4;   // for JAL return address
    reg [4:0]  EX_MEM_rd;
    reg        EX_MEM_mem_to_reg, EX_MEM_reg_write;
    reg        EX_MEM_mem_read,   EX_MEM_mem_write;
    reg        EX_MEM_jal;

    always @(posedge clk or posedge rst) begin
        if (rst) begin
            EX_MEM_alu_result  <= 32'h0;
            EX_MEM_reg_rdata2  <= 32'h0;
            EX_MEM_pc_plus4    <= 32'h0;
            EX_MEM_rd          <= 5'h0;
            EX_MEM_mem_to_reg  <= 1'b0;
            EX_MEM_reg_write   <= 1'b0;
            EX_MEM_mem_read    <= 1'b0;
            EX_MEM_mem_write   <= 1'b0;
            EX_MEM_jal         <= 1'b0;
        end else begin
            EX_MEM_alu_result  <= alu_result;
            EX_MEM_reg_rdata2  <= forward_b_out;
            EX_MEM_pc_plus4    <= pc_plus4_ex;  // FIX 2
            EX_MEM_rd          <= ID_EX_rd;
            EX_MEM_mem_to_reg  <= ID_EX_mem_to_reg;
            EX_MEM_reg_write   <= ID_EX_reg_write;
            EX_MEM_mem_read    <= ID_EX_mem_read;
            EX_MEM_mem_write   <= ID_EX_mem_write;
            EX_MEM_jal         <= ID_EX_jal;
        end
    end

// ============================================================
// MEM STAGE — Memory Access
// ============================================================
    reg  [31:0] data_mem [0:255];
    wire [31:0] mem_read_data;

    assign mem_read_data = data_mem[EX_MEM_alu_result[9:2]];

    always @(posedge clk) begin
        if (EX_MEM_mem_write)
            data_mem[EX_MEM_alu_result[9:2]] <= EX_MEM_reg_rdata2;
    end

// ============================================================
// MEM/WB PIPELINE REGISTER
// ============================================================
    reg [31:0] MEM_WB_alu_result, MEM_WB_mem_data;
    reg [31:0] MEM_WB_pc_plus4;
    reg [4:0]  MEM_WB_rd;
    reg        MEM_WB_mem_to_reg, MEM_WB_reg_write;
    reg        MEM_WB_jal;

    always @(posedge clk or posedge rst) begin
        if (rst) begin
            MEM_WB_alu_result <= 32'h0;
            MEM_WB_mem_data   <= 32'h0;
            MEM_WB_pc_plus4   <= 32'h0;
            MEM_WB_rd         <= 5'h0;
            MEM_WB_mem_to_reg <= 1'b0;
            MEM_WB_reg_write  <= 1'b0;
            MEM_WB_jal        <= 1'b0;
        end else begin
            MEM_WB_alu_result <= EX_MEM_alu_result;
            MEM_WB_mem_data   <= mem_read_data;
            MEM_WB_pc_plus4   <= EX_MEM_pc_plus4;
            MEM_WB_rd         <= EX_MEM_rd;
            MEM_WB_mem_to_reg <= EX_MEM_mem_to_reg;
            MEM_WB_reg_write  <= EX_MEM_reg_write;
            MEM_WB_jal        <= EX_MEM_jal;
        end
    end

// ============================================================
// WB STAGE — Write Back
// FIX 2: JAL writes PC+4 (return address), not ALU result
// ============================================================
    always @(*) begin
        if (MEM_WB_jal)
            reg_wdata_wb = MEM_WB_pc_plus4;         // JAL: return address
        else if (MEM_WB_mem_to_reg)
            reg_wdata_wb = MEM_WB_mem_data;          // Load
        else
            reg_wdata_wb = MEM_WB_alu_result;        // ALU result
        reg_waddr_wb = MEM_WB_rd;
        reg_write_wb = MEM_WB_reg_write;
    end

// ============================================================
// CPI PERFORMANCE COUNTER (Fix 5 — new addition)
// ============================================================
    reg [31:0] cycle_count;
    reg [31:0] instr_count;
    reg [31:0] stall_count;

    always @(posedge clk or posedge rst) begin
        if (rst) begin
            cycle_count <= 32'h0;
            instr_count <= 32'h0;
            stall_count <= 32'h0;
        end else begin
            cycle_count <= cycle_count + 1;
            if (stall)
                stall_count <= stall_count + 1;
            // Count instruction when it leaves ID stage (not a bubble)
            if (!stall && (IF_ID_instr != 32'h00000013) && (IF_ID_instr != 32'h0))
                instr_count <= instr_count + 1;
        end
    end

endmodule

rtl/tb_cpu.v
`timescale 1ns/1ps

// ============================================================
// tb_cpu.v — Testbench for pipeline_cpu
// ============================================================
module tb_cpu;

    reg clk, rst;

    pipeline_cpu uut (
        .clk(clk),
        .rst(rst)
    );

    // 10ns clock period
    initial begin
        clk = 0;
        forever #5 clk = ~clk;
    end

    initial begin
        $dumpfile("dump.vcd");
        $dumpvars(0, tb_cpu);

        rst = 1;
        #20;
        rst = 0;

        // Run for enough cycles
        #400;

        $display("\n========== FINAL RESULTS ==========");
        $display("x1  = %0d (Expected: 36 - JAL return address)", uut.regs[1]);
        $display("x2  = %0d (Expected: 30)",                      uut.regs[2]);
        $display("x3  = %0d (Expected: 30)",                      uut.regs[3]);
        $display("x4  = %0d (Expected: 50)",                      uut.regs[4]);
        $display("x5  = %0d (Expected: 40)",                      uut.regs[5]);
        $display("mem[0] = %0d (Expected: 50)",                   uut.data_mem[0]);
        $display("===================================");

        // CPI report
        $display("\n========== PERFORMANCE ==========");
        $display("Total cycles     : %0d", uut.cycle_count);
        $display("Instructions     : %0d", uut.instr_count);
        $display("Stall cycles     : %0d", uut.stall_count);
        if (uut.instr_count > 0)
            $display("CPI              : %0d.%02d",
                uut.cycle_count / uut.instr_count,
                ((uut.cycle_count * 100) / uut.instr_count) % 100);
        $display("=================================");

        // Pass/Fail check
        $display("\n========== TEST STATUS ==========");
        if (uut.regs[1]==36 && uut.regs[2]==30 && uut.regs[3]==30 &&
            uut.regs[4]==50 && uut.regs[5]==40 && uut.data_mem[0]==50)
            $display("ALL TESTS PASSED ✓");
        else
            $display("SOME TESTS FAILED ✗");
        $display("=================================\n");

        $finish;
    end

    // Pipeline state monitor
    always @(negedge clk) begin
        if (!rst)
            $display("Time=%0t | PC=%0d | IF_ID=%h | EX_ALU=%0d | stall=%b | x1=%0d x2=%0d x3=%0d x4=%0d x5=%0d",
                $time,
                uut.PC,
                uut.IF_ID_instr,
                uut.EX_MEM_alu_result,
                uut.stall,
                uut.regs[1], uut.regs[2], uut.regs[3],
                uut.regs[4], uut.regs[5]);
    end

endmodule

dump.vcd
$date
	Sat Mar 28 20:55:25 2026
$end
$version
	Icarus Verilog
$end
$timescale
	1ps
$end
$scope module tb_cpu $end
$var reg 1 ! clk $end
$var reg 1 " rst $end
$scope module uut $end
$var wire 32 # alu_in_a [31:0] $end
$var wire 1 $ branch_taken $end
$var wire 1 ! clk $end
$var wire 1 % flush_if_id $end
$var wire 32 & instr [31:0] $end
$var wire 32 ' mem_read_data [31:0] $end
$var wire 1 " rst $end
$var wire 1 ( stall $end
$var wire 32 ) wb_data [31:0] $end
$var wire 32 * reg_rdata2 [31:0] $end
$var wire 32 + reg_rdata1 [31:0] $end
$var wire 32 , pc_plus4_ex [31:0] $end
$var wire 32 - pc_plus4 [31:0] $end
$var wire 32 . pc_next [31:0] $end
$var wire 32 / jalr_target [31:0] $end
$var wire 32 0 jal_target [31:0] $end
$var wire 32 1 imm_out [31:0] $end
$var wire 2 2 forward_b_sel [1:0] $end
$var wire 32 3 forward_b_out [31:0] $end
$var wire 2 4 forward_a_sel [1:0] $end
$var wire 32 5 forward_a_out [31:0] $end
$var wire 1 6 ctrl_reg_write $end
$var wire 1 7 ctrl_mem_write $end
$var wire 1 8 ctrl_mem_to_reg $end
$var wire 1 9 ctrl_mem_read $end
$var wire 1 : ctrl_jalr $end
$var wire 1 ; ctrl_jal $end
$var wire 1 < ctrl_branch $end
$var wire 1 = ctrl_alu_src $end
$var wire 4 > ctrl_alu_op [3:0] $end
$var wire 32 ? branch_target [31:0] $end
$var wire 1 @ alu_zero $end
$var wire 32 A alu_result [31:0] $end
$var wire 32 B alu_in_b [31:0] $end
$var wire 5 C IF_ID_rs2 [4:0] $end
$var wire 5 D IF_ID_rs1 [4:0] $end
$var wire 5 E IF_ID_rd [4:0] $end
$var wire 7 F IF_ID_opcode [6:0] $end
$var reg 32 G EX_MEM_alu_result [31:0] $end
$var reg 1 H EX_MEM_jal $end
$var reg 1 I EX_MEM_mem_read $end
$var reg 1 J EX_MEM_mem_to_reg $end
$var reg 1 K EX_MEM_mem_write $end
$var reg 32 L EX_MEM_pc_plus4 [31:0] $end
$var reg 5 M EX_MEM_rd [4:0] $end
$var reg 32 N EX_MEM_reg_rdata2 [31:0] $end
$var reg 1 O EX_MEM_reg_write $end
$var reg 4 P ID_EX_alu_op [3:0] $end
$var reg 1 Q ID_EX_alu_src $end
$var reg 1 R ID_EX_branch $end
$var reg 3 S ID_EX_funct3 [2:0] $end
$var reg 1 T ID_EX_funct7_5 $end
$var reg 32 U ID_EX_imm [31:0] $end
$var reg 1 V ID_EX_jal $end
$var reg 1 W ID_EX_jalr $end
$var reg 1 X ID_EX_mem_read $end
$var reg 1 Y ID_EX_mem_to_reg $end
$var reg 1 Z ID_EX_mem_write $end
$var reg 32 [ ID_EX_pc [31:0] $end
$var reg 5 \ ID_EX_rd [4:0] $end
$var reg 32 ] ID_EX_reg_rdata1 [31:0] $end
$var reg 32 ^ ID_EX_reg_rdata2 [31:0] $end
$var reg 1 _ ID_EX_reg_write $end
$var reg 5 ` ID_EX_rs1 [4:0] $end
$var reg 5 a ID_EX_rs2 [4:0] $end
$var reg 32 b IF_ID_instr [31:0] $end
$var reg 32 c IF_ID_pc [31:0] $end
$var reg 32 d MEM_WB_alu_result [31:0] $end
$var reg 1 e MEM_WB_jal $end
$var reg 32 f MEM_WB_mem_data [31:0] $end
$var reg 1 g MEM_WB_mem_to_reg $end
$var reg 32 h MEM_WB_pc_plus4 [31:0] $end
$var reg 5 i MEM_WB_rd [4:0] $end
$var reg 1 j MEM_WB_reg_write $end
$var reg 32 k PC [31:0] $end
$var reg 32 l cycle_count [31:0] $end
$var reg 4 m ex_alu_op [3:0] $end
$var reg 32 n instr_count [31:0] $end
$var reg 5 o reg_waddr_wb [4:0] $end
$var reg 32 p reg_wdata_wb [31:0] $end
$var reg 1 q reg_write_wb $end
$var reg 32 r stall_count [31:0] $end
$var integer 32 s k [31:0] $end
$scope module alu_inst $end
$var wire 32 t a [31:0] $end
$var wire 4 u alu_op [3:0] $end
$var wire 32 v b [31:0] $end
$var wire 3 w funct3 [2:0] $end
$var wire 1 T funct7_5 $end
$var wire 1 @ zero $end
$var wire 5 x shamt [4:0] $end
$var reg 32 y result [31:0] $end
$upscope $end
$scope module ctrl_inst $end
$var wire 7 z opcode [6:0] $end
$var reg 4 { alu_op [3:0] $end
$var reg 1 = alu_src $end
$var reg 1 < branch $end
$var reg 1 ; jal $end
$var reg 1 : jalr $end
$var reg 1 9 mem_read $end
$var reg 1 8 mem_to_reg $end
$var reg 1 7 mem_write $end
$var reg 1 6 reg_write $end
$upscope $end
$scope module imm_gen_inst $end
$var wire 32 | instr [31:0] $end
$var wire 7 } opcode [6:0] $end
$var reg 32 ~ imm [31:0] $end
$upscope $end
$upscope $end
$upscope $end
$enddefinitions $end
#0
$dumpvars
b0 ~
b10011 }
b10011 |
b0 {
b10011 z
b0 y
b0 x
b0 w
b0 v
b0 u
b0 t
b100000 s
b0 r
0q
b0 p
b0 o
b0 n
b0 m
b0 l
b0 k
0j
b0 i
b0 h
0g
b0 f
0e
b0 d
b0 c
b10011 b
b0 a
b0 `
0_
b0 ^
b0 ]
b0 \
b0 [
0Z
0Y
0X
0W
0V
b0 U
0T
b0 S
0R
0Q
b0 P
0O
b0 N
b0 M
b0 L
0K
0J
0I
0H
b0 G
b10011 F
b0 E
b0 D
b0 C
b0 B
b0 A
1@
b0 ?
b0 >
1=
0<
0;
0:
09
08
07
16
b0 5
b0 4
b0 3
b0 2
b0 1
b0 0
b0 /
b100 .
b100 -
b100 ,
b0 +
b0 *
b0 )
0(
bx '
b101000000000000010010011 &
0%
0$
b0 #
1"
0!
$end
#5000
1!
#10000
0!
#15000
1!
#20000
0!
0"
#25000
b1000 .
b1010 C
b1 E
b1010 1
b1010 ~
b1010000000000000100010011 &
b1 l
bx f
b100 L
1_
1Q
b101000000000000010010011 b
b101000000000000010010011 |
b1000 -
b100 k
1!
#30000
0!
#35000
b1100 .
b1010 /
0@
b1010 A
b1010 y
b1010 x
b1000001000000110110011 &
b10100 C
b10 E
b10100 1
b10100 ~
b1010 B
b1010 v
b1100 -
b1000 k
b1010000000000000100010011 b
b1010000000000000100010011 |
b100 c
b1 \
b1010 a
b1010 ?
b1010 0
b1010 U
1O
b100 h
b1 n
b10 l
1!
#40000
0!
#45000
b10100 /
b10000 .
b10100 A
b10100 y
b10100 x
16
0=
1q
b10100 B
b10100 v
b110011 F
b110011 z
b1 D
b10 C
b11 E
b0 1
b0 ~
b110011 }
b1100010000001000110011 &
b10 n
b11 l
1j
b1 M
b1010 G
b10 \
b10100 a
b10100 U
b11000 ?
b11000 0
b1000 ,
b100 [
b1000001000000110110011 b
b1000001000000110110011 |
b1000 c
b10000 -
b1100 k
1!
#50000
0!
#55000
b1010 #
b1010 t
b1010 5
b1 4
b10100 .
b10100 3
b11110 /
b10 2
0@
b11110 A
b11110 y
b10100 x
b10000000010000000100011 &
b10 D
b11 C
b100 E
b10100 B
b10100 v
b1 o
b1010 p
b1010 )
b10100 -
b10000 k
b1100010000001000110011 b
b1100010000001000110011 |
b1100 c
0Q
b11 \
b10 a
b1 `
b0 U
b1000 ?
b1000 0
b1100 ,
b1000 [
b10 M
b1000 L
b10100 G
b1 i
b1010 d
b11 n
b100 l
1!
#60000
0!
#65000
b110010 /
b10100 #
b10100 t
b10100 5
b110010 A
b110010 y
b11110 x
b11000 .
b11110 B
b11110 v
17
1=
06
b10 o
b10100 p
b10100 )
b11110 3
b100011 F
b100011 z
b0 D
b100 C
b0 E
b100011 }
b10001010000011 &
b100 n
b101 l
b10 i
b1000 h
b10100 d
b11 M
b1100 L
b10100 N
b11110 G
b100 \
b11 a
b10 `
b1100 ?
b1100 0
b10000 ,
b1100 [
b10000000010000000100011 b
b10000000010000000100011 |
b10000 c
b11000 -
b10100 k
1!
#70000
0!
#75000
b11100 .
b0 /
b0 4
b0 #
b0 t
b0 5
19
16
18
07
1=
b0 x
1@
b0 A
b0 y
b1000001001001001100011 &
b11 F
b11 z
b0 C
b101 E
b11 }
b0 B
b0 v
b11 m
b11 u
b110010 3
b11 o
b11110 p
b11110 )
b11100 -
b11000 k
b10001010000011 b
b10001010000011 |
b10100 c
1Z
0_
1Q
b10 S
b10 w
b0 \
b100 a
b0 `
b10000 ?
b10000 0
b10100 ,
b10000 [
b100 M
b10000 L
b11110 N
b110010 G
b11 i
b1100 h
b11110 d
b101 n
b110 l
1!
#80000
0!
#85000
b0 2
b100000 .
b0 4
1<
b1 >
b1 {
09
06
08
0=
b11 m
b11 u
b1010 +
b10100 *
b100 o
b110010 p
b110010 )
b0 3
b1100011 F
b1100011 z
b1 D
b10 C
b100 E
b100 1
b100 ~
b1100011 }
b100010000000100110011 &
b110 n
b111 l
b100 i
b10000 h
b110010 d
1K
0O
b0 M
b10100 L
b110010 N
b0 G
0Z
1X
1_
1Y
b101 \
b0 a
b10100 ?
b10100 0
b11000 ,
b10100 [
b1000001001001001100011 b
b1000001001001001100011 |
b11000 c
b100000 -
b11100 k
1!
#90000
0!
